temp/probador_me.v
// Declaración del módulo y parámetros
 module probador #(parameter SECUENCIA = 5'b10100,
                   parameter SEC_REINICIO = 5'b00000) (clk,rst,s_in,valido,nuevo_numero); 
  // Declaración de entradas y salidas
 output reg clk,rst,s_in;
 input  valido,nuevo_numero;

    initial begin
    clk = 0;
    rst = 0;
    s_in = 0;
    #25 rst = 1;
    #15 rst = 0;
//Código inválido
    #10 s_in = 1;
    #10 s_in = 1;
    #10 s_in = 0;
    #10 s_in = 1;
    #10 s_in = 1;
//Código válido
    #10 s_in = 1;
    #10 s_in = 0;
    #10 s_in = 1;
    #10 s_in = 0;
    #10 s_in = 0;
//Ya sincronizado
    #10 s_in = 1;
    #10 s_in = 1;
    #10 s_in = 0;
    #10 s_in = 0;
    #10 s_in = 1;
//Pierde sincronía
    #10 s_in = 0;
    #10 s_in = 0;
    #10 s_in = 0;
    #10 s_in = 0;
    #10 s_in = 0;
    #30 $finish;
  end

  always begin
    #5 clk = !clk;
  end
  
endmodule

temp/me_op1.v
// Declaración del módulo y parámetros
module det_sec #(parameter SECUENCIA = 5'b10100,
                 parameter SEC_REINICIO = 5'b00000) (clk,rst,s_in,valido, nuevo_numero);

// Declaración de entradas y salidas
input clk,rst,s_in;
output reg valido,nuevo_numero;

//Declaración de variables internas
reg   [4:0] sec_recibida;

//Se usan dos bits para que sea un flip flop por estado (one-hot encoding) que elimina las carreras
//de estado (race conditions)
//INICIO = 01
//SINCRONIZADO = 10
//
reg   [1:0] estado_actual;
reg   [1:0] prox_estado;

//Definir todos los flip flops
always @(posedge clk) begin
	if (rst) begin 
	   estado_actual <= 2'b01;
	   sec_recibida  <= '0;
	end
	else begin
	   estado_actual   <= prox_estado;
	   sec_recibida[0] <= s_in;
	   sec_recibida[1] <= sec_recibida[0];
	   sec_recibida[2] <= sec_recibida[1];
           sec_recibida[3] <= sec_recibida[2];
	   sec_recibida[4] <= sec_recibida[3];
	end

end

//Definir lógica combinacional
//Case de los estados
always @(*) begin
  prox_estado = estado_actual;
  //Case de estados para definir:
  //1. Lógica de próximo estado
  //2. Lógica de salida
  case (estado_actual)
    //Estado de inicio
    2'b01: begin
	     valido = 0;
             if (sec_recibida == SECUENCIA) prox_estado = 2'b10;
	     else prox_estado = 2'b01;
           end
    //Estado sincronizado
    2'b10: begin 
             valido = 1;
             if (sec_recibida == SEC_REINICIO) prox_estado = 2'b01;
	     else prox_estado = 2'b10;
           end
    //Cualquier otro caso
    default: begin 
               valido = 0;
               prox_estado = 2'b01;
             end
  endcase

end
// lógica de salida nuevo_numero
always @(*) begin
  nuevo_numero = ((estado_actual == 2'b01) & (clk) & (~rst));
end


endmodule

temp/testbench_me.v
`include "probador_me.v"
`include "me_op1.v"

// Testbench Code
module me_tb;

  // Declaración de señales
  wire clk, rst, s_in, valido, nuevo_numero;

  // Configuración de señales de volcado para la simulación
  initial begin
    $dumpfile("resultados.vcd");
    $dumpvars(-1, MEOP1); // Volcar todas las señales del módulo `MEOP1`
  end

  // Instancia del módulo secuenciador (det_sec)
  det_sec MEOP1 (
    .clk (clk),
    .rst (rst),
    .s_in (s_in),
    .valido (valido),
    .nuevo_numero (nuevo_numero)  // Nueva conexión para la señal nuevo_numero
  );

  // Instancia del probador
  probador PROB_MEOP1 (
    .clk (clk),
    .rst (rst),
    .s_in (s_in),
    .valido (valido),
    .nuevo_numero (nuevo_numero)  // Conectar la nueva señal
  );

endmodule

temp/resultados.vcd
$date
	Mon Sep 30 11:40:15 2024
$end
$version
	Icarus Verilog
$end
$timescale
	1s
$end
$scope module me_tb $end
$scope module MEOP1 $end
$var wire 1 ! s_in $end
$var wire 1 " rst $end
$var wire 1 # clk $end
$var parameter 5 $ SECUENCIA $end
$var parameter 5 % SEC_REINICIO $end
$var reg 2 & estado_actual [1:0] $end
$var reg 1 ' nuevo_numero $end
$var reg 2 ( prox_estado [1:0] $end
$var reg 5 ) sec_recibida [4:0] $end
$var reg 1 * valido $end
$upscope $end
$upscope $end
$enddefinitions $end
$comment Show the parameter values. $end
$dumpall
b0 %
b10100 $
$end
#0
$dumpvars
x*
bx )
bx (
0'
bx &
0#
0"
0!
$end
#5
b1 (
0*
bx0 )
x'
1#
#10
0'
0#
#15
bx00 )
b1 &
1'
1#
#20
0'
0#
#25
b0 )
1#
1"
#30
0#
#35
1#
#40
0#
0"
#45
1'
1#
#50
0'
0#
1!
#55
b1 )
1'
1#
#60
0'
0#
#65
b11 )
1'
1#
#70
0'
0#
0!
#75
b110 )
1'
1#
#80
0'
0#
1!
#85
b1101 )
1'
1#
#90
0'
0#
#95
b11011 )
1'
1#
#100
0'
0#
#105
b10111 )
1'
1#
#110
0'
0#
0!
#115
b1110 )
1'
1#
#120
0'
0#
1!
#125
b11101 )
1'
1#
#130
0'
0#
0!
#135
b11010 )
1'
1#
#140
0'
0#
#145
b10 (
b10100 )
1'
1#
#150
0'
0#
1!
#155
1*
b1001 )
b10 &
0'
1#
#160
0#
#165
b10011 )
1#
#170
0#
0!
#175
b110 )
1#
#180
0#
#185
b1100 )
1#
#190
0#
1!
#195
b11001 )
1#
#200
0#
0!
#205
b10010 )
1#
#210
0#
#215
b100 )
1#
#220
0#
#225
b1000 )
1#
#230
0#
#235
b10000 )
1#
#240
0#
#245
b1 (
b0 )
1#
#250
0#
#255
1'
0*
b1 &
1#
#260
0'
0#
#265
1'
1#
#270
0'
0#
