tarea 3/provador.v
module provador (
    output reg clk, rst,TARJETA_RECIBIDA, TIPO_TRNANS, DIGITO_STB, MONTO_STB,
    input  ENTREGAR_DINERO, PIN_INCORRECTO, ADVERTENCIA, BLOQUEO, FONDOS_INSUFICIENTES, BALANCE_ACTUALIZADO,
    output reg [3:0] DIGITO,
    output reg [15:0] PIN,
    output reg [31:0] MONTO,
    output reg [63:0] BALANCE_INICIAL
);

    initial begin
        clk = 0; 
        rst = 0;
        BALANCE_INICIAL = 64'd20000; // Inicializar balance a 20,000
        PIN = 16'h1194; // Inicializar PIN a 1194
        TARJETA_RECIBIDA = 0; DIGITO_STB = 0; TIPO_TRNANS = 0; MONTO_STB = 0;

//Caso 1 deposito perfecto 
        #(10) rst = 0;                              
        #(10) rst = 1;                                


        #(20) TARJETA_RECIBIDA = 1'b1;
        #(20) DIGITO = 4'h1;
        #(20) DIGITO = 4'h1;
        #(20) DIGITO = 4'h9;                          
        #(20) DIGITO = 4'h4;
         
         //prox estado = tipo de transación 
        #(20) DIGITO_STB = 1;  

        //estado presente tipo de transacción
        #(20) TARJETA_RECIBIDA = 0; DIGITO_STB = 0; TIPO_TRNANS = 0;

        //estado presente = deposito
        #(20) MONTO = 32'd15000; MONTO_STB = 1; 
        


//caso 2 retiro perfecto
        //estado presente esperando tarjeta
        #(40) MONTO_STB = 0; MONTO = 32'd0;

        //prox estado = esperando pin 
        #(20) TARJETA_RECIBIDA = 1'b1;

        //estado presente = esperando pin
        #(20) DIGITO = 4'h1;
        #(20) DIGITO = 4'h1;
        #(20) DIGITO = 4'h9; TARJETA_RECIBIDA = 0;  
        #(20) DIGITO = 4'h4;

        //prox estado = tipo de transación
        #(20) DIGITO_STB = 1; 

        //estado presente = tipo de transación
        #(20) DIGITO_STB = 0; TIPO_TRNANS = 1;

        //estado presente = retiro
        #(20) MONTO = 32'd15000;

        //prox estado = esperando tarjeta 
        #(20) MONTO_STB = 1;  TIPO_TRNANS = 0;
        #(20) MONTO_STB = 0; MONTO = 32'd0;

//caso 3 clave 3 veces incorrecta

        //prox estado = ingresando pin
        #(20) TARJETA_RECIBIDA = 1;
        //estado presente = ingresando pin
        #(20) DIGITO = 4'h1;
        #(20) DIGITO = 4'h1;
        #(20) DIGITO = 4'h9; TARJETA_RECIBIDA = 0;
        #(20) DIGITO = 4'h5;
        #(20) DIGITO_STB = 1;
        #(20) DIGITO_STB = 0;
        #(20) DIGITO_STB = 1;
        #(20) DIGITO_STB = 0;
        #(20) DIGITO_STB = 1;
        #(20) DIGITO_STB = 0;
        //proximo estado = esperando tarjeta
        #(40) rst = 0;
        //estado presente = esperando tarjeta
        #(20) rst = 1;



        //caso 4 retiro fallido
        //proximo estado = ingresando pin
        #(20) TARJETA_RECIBIDA = 1'b1;
        #(20) DIGITO = 4'h1;
        #(20) DIGITO = 4'h1;
        #(20) DIGITO = 4'h9; TARJETA_RECIBIDA = 0;

        //proximo estado = tipo trans
        #(20) DIGITO = 4'h4; DIGITO_STB = 1;

        //proximo estado = retiro
        #(20) TIPO_TRNANS = 1;

        //estado presente = retiro
        #(20) DIGITO_STB = 0; MONTO = 32'd45000;

        #(20) MONTO_STB = 1;  TIPO_TRNANS = 0;
        #(20) MONTO_STB = 0; MONTO = 32'd0;
        #(20) DIGITO_STB = 0; MONTO = 32'd10000;
        #(20) MONTO_STB = 1;  TIPO_TRNANS = 0;
        #(20) MONTO_STB = 0; MONTO = 32'd0;


  







        #(100) $finish;
    end

    // Generación de reloj
    always begin
        #(10) clk = ~clk;
    end

endmodule

tarea 3/cajero.v
module cajero (
    clk,rst,TARJETA_RECIBIDA,TIPO_TRNANS,DIGITO,DIGITO_STB,PIN,MONTO,MONTO_STB,BALANCE_INICIAL,
    BALANCE_ACTUALIZADO,ENTREGAR_DINERO,PIN_INCORRECTO,ADVERTENCIA,BLOQUEO,FONDOS_INSUFICIENTES
);
    input  clk, rst, TARJETA_RECIBIDA, TIPO_TRNANS, DIGITO_STB, MONTO_STB;
    output reg ENTREGAR_DINERO, PIN_INCORRECTO, ADVERTENCIA, BLOQUEO, FONDOS_INSUFICIENTES, BALANCE_ACTUALIZADO;
    input wire [3:0] DIGITO;
    input wire [15:0] PIN;
    input wire [31:0] MONTO;
    input wire [63:0] BALANCE_INICIAL;

    reg [1:0] contador_intentos, prox_contador_intentos;
    reg [15:0] pin_recibido;
    reg [2:0] EstPresente, ProxEstado;
    reg [63:0] Balance;

    // Lógica de asignación de estados
    localparam Esperando_tarjeta = 3'b000;
    localparam Ingresando_pin = 3'b001;
    localparam E_Bloqueo = 3'b010;
    localparam Deposito = 3'b011;
    localparam Retiro = 3'b100;
    localparam Tipo_de_trans = 3'b101;

    // Memoria de estados
    always @(posedge clk) begin
        if (~rst) begin
            EstPresente <= Esperando_tarjeta;
            contador_intentos <= 2'b00;
            pin_recibido <= 16'h0;
            Balance <= BALANCE_INICIAL;
        end 
        else begin
            EstPresente <= ProxEstado;
            contador_intentos <= prox_contador_intentos;
            pin_recibido[3:0] <= DIGITO[3:0];
            pin_recibido[7:4] <= pin_recibido[3:0];
            pin_recibido[11:8] <= pin_recibido[7:4];
            pin_recibido[15:12] <= pin_recibido[11:8];
        end
    end

    always @(*) begin
        // Asignación por defecto de salidas (apagadas)
        ENTREGAR_DINERO = 1'b0;
        PIN_INCORRECTO = 1'b0;
        ADVERTENCIA = 1'b0;
        BLOQUEO = 1'b0;
        FONDOS_INSUFICIENTES = 1'b0;
        BALANCE_ACTUALIZADO = 1'b0;
        pin_recibido = 16'b0;

        
        // Por defecto
        prox_contador_intentos = contador_intentos;
        Balance = BALANCE_INICIAL;
        ProxEstado = EstPresente;
        pin_recibido = 16'b0;
        
        case (EstPresente)
        
        // Estado Esperando_tarjeta
        Esperando_tarjeta: begin
            if (TARJETA_RECIBIDA) begin
                ProxEstado = Ingresando_pin;
                prox_contador_intentos = 2'b00;
            end
            else begin
                ProxEstado = Esperando_tarjeta;
            end
        end
        
        // Estado Ingresando_pin
        Ingresando_pin: begin
            if (DIGITO_STB) begin
                if (pin_recibido == PIN) begin
                    ProxEstado = Tipo_de_trans;
                    prox_contador_intentos = 2'b00;  // Reinicio de intentos
                end
                else if (contador_intentos == 3) begin  // Tercer intento fallido
                    BLOQUEO = 1'b1;
                    ProxEstado = E_Bloqueo;
                end
                else if (contador_intentos == 2) begin  // Segundo intento fallido (advertencia)
                    ADVERTENCIA = 1'b1;
                    ProxEstado = Ingresando_pin;
                    prox_contador_intentos = contador_intentos + 1;
                end
                else begin  // Primer intento fallido
                    PIN_INCORRECTO = 1'b1;
                    prox_contador_intentos = contador_intentos + 1;
                end
            end
            else if (contador_intentos == 3) begin
                ProxEstado = E_Bloqueo;
                BLOQUEO = 1'b1;
            end
            else begin
                ProxEstado = Ingresando_pin;
            end
        end

        // Estado Tipo_de_trans
        Tipo_de_trans: begin
            if (TIPO_TRNANS) begin
                ProxEstado = Retiro;
            end
            else begin
                ProxEstado = Deposito;
            end
        end

        // Estado Retiro
        Retiro: begin
            if (MONTO_STB) begin
                if (MONTO <= BALANCE_INICIAL) begin
                    Balance = BALANCE_INICIAL - MONTO;
                    BALANCE_ACTUALIZADO = 1'b1;
                    ENTREGAR_DINERO = 1'b1;
                    ProxEstado = Esperando_tarjeta;
                end
                else begin
                    FONDOS_INSUFICIENTES = 1'b1;
                    ProxEstado = Retiro;
                end
            end
            else begin
                ProxEstado = Retiro;
            end
        end

        // Estado Deposito
        Deposito: begin
            if (MONTO_STB) begin
                if (MONTO != 32'b0) begin
                    Balance = BALANCE_INICIAL + MONTO;
                    BALANCE_ACTUALIZADO = 1'b1;
                    ProxEstado = Esperando_tarjeta;
                end
                else begin
                    ProxEstado = Deposito;
                end
            end
            else begin
                ProxEstado = Deposito;
            end
        end

        // Estado E_Bloqueo
        E_Bloqueo: begin
            if (~rst) begin
                ProxEstado = Esperando_tarjeta;
            end
            else begin
                ProxEstado = E_Bloqueo;
                BLOQUEO = 1'b1;
            end
        end
        default: begin
            ProxEstado = Esperando_tarjeta;
        end
        
        endcase
    end

endmodule

tarea 3/testbench.v
`include "cajero.v"
`include "provador.v"

module cajero_tb;
    // Declaración de señales
    wire clk, rst;
    wire TARJETA_RECIBIDA, TIPO_TRNANS, DIGITO_STB, MONTO_STB;
    wire ENTREGAR_DINERO, PIN_INCORRECTO, ADVERTENCIA, BLOQUEO, FONDOS_INSUFICIENTES, BALANCE_ACTUALIZADO;
    wire [3:0] DIGITO;
    wire [15:0] PIN;
    wire [31:0] MONTO;
    wire [63:0] BALANCE_INICIAL;

    // Instancia del módulo cajero
    cajero U0 (
        .clk(clk),
        .rst(rst),
        .TARJETA_RECIBIDA(TARJETA_RECIBIDA),
        .TIPO_TRNANS(TIPO_TRNANS),
        .DIGITO_STB(DIGITO_STB),
        .MONTO_STB(MONTO_STB),
        .ENTREGAR_DINERO(ENTREGAR_DINERO),
        .PIN_INCORRECTO(PIN_INCORRECTO),
        .ADVERTENCIA(ADVERTENCIA),
        .BLOQUEO(BLOQUEO),
        .FONDOS_INSUFICIENTES(FONDOS_INSUFICIENTES),
        .BALANCE_ACTUALIZADO(BALANCE_ACTUALIZADO),
        .DIGITO(DIGITO),
        .PIN(PIN),
        .MONTO(MONTO),
        .BALANCE_INICIAL(BALANCE_INICIAL)
    );

    // Instancia del módulo provador
    provador P0 (
        .clk(clk),
        .rst(rst),
        .TARJETA_RECIBIDA(TARJETA_RECIBIDA),
        .TIPO_TRNANS(TIPO_TRNANS),
        .DIGITO_STB(DIGITO_STB),
        .MONTO_STB(MONTO_STB),
        .ENTREGAR_DINERO(ENTREGAR_DINERO),
        .PIN_INCORRECTO(PIN_INCORRECTO),
        .ADVERTENCIA(ADVERTENCIA),
        .BLOQUEO(BLOQUEO),
        .FONDOS_INSUFICIENTES(FONDOS_INSUFICIENTES),
        .BALANCE_ACTUALIZADO(BALANCE_ACTUALIZADO),
        .DIGITO(DIGITO),
        .PIN(PIN),
        .MONTO(MONTO),
        .BALANCE_INICIAL(BALANCE_INICIAL)
    );

     // Bloque inicial para la simulación
    initial begin
        $dumpfile("resultados.vcd");
        $dumpvars(-1, U0);
        // Monitorización de todas las señales
        $monitor("clk=%b rst=%b TARJETA_RECIBIDA=%b TIPO_TRNANS=%b DIGITO_STB=%b MONTO_STB=%b ENTREGAR_DINERO=%b PIN_INCORRECTO=%b ADVERTENCIA=%b BLOQUEO=%b FONDOS_INSUFICIENTES=%b BALANCE_ACTUALIZADO=%b DIGITO=%b PIN=%b MONTO=%b BALANCE_INICIAL=%b",
                 clk, rst, TARJETA_RECIBIDA, TIPO_TRNANS, DIGITO_STB, MONTO_STB, ENTREGAR_DINERO, PIN_INCORRECTO, ADVERTENCIA, BLOQUEO, FONDOS_INSUFICIENTES, BALANCE_ACTUALIZADO, DIGITO, PIN, MONTO, BALANCE_INICIAL);
    end
endmodule

tarea 3/resultados.vcd
$date
	Tue Oct 01 07:28:34 2024
$end
$version
	Icarus Verilog
$end
$timescale
	1s
$end
$scope module cajero_tb $end
$scope module U0 $end
$var wire 64 ! BALANCE_INICIAL [63:0] $end
$var wire 4 " DIGITO [3:0] $end
$var wire 1 # DIGITO_STB $end
$var wire 32 $ MONTO [31:0] $end
$var wire 1 % MONTO_STB $end
$var wire 16 & PIN [15:0] $end
$var wire 1 ' TARJETA_RECIBIDA $end
$var wire 1 ( TIPO_TRNANS $end
$var wire 1 ) clk $end
$var wire 1 * rst $end
$var parameter 3 + Deposito $end
$var parameter 3 , E_Bloqueo $end
$var parameter 3 - Esperando_tarjeta $end
$var parameter 3 . Ingresando_pin $end
$var parameter 3 / Retiro $end
$var parameter 3 0 Tipo_de_trans $end
$var reg 1 1 ADVERTENCIA $end
$var reg 1 2 BALANCE_ACTUALIZADO $end
$var reg 1 3 BLOQUEO $end
$var reg 64 4 Balance [63:0] $end
$var reg 1 5 ENTREGAR_DINERO $end
$var reg 3 6 EstPresente [2:0] $end
$var reg 1 7 FONDOS_INSUFICIENTES $end
$var reg 1 8 PIN_INCORRECTO $end
$var reg 3 9 ProxEstado [2:0] $end
$var reg 2 : contador_intentos [1:0] $end
$var reg 16 ; pin_recibido [15:0] $end
$var reg 2 < prox_contador_intentos [1:0] $end
$upscope $end
$upscope $end
$enddefinitions $end
$comment Show the parameter values. $end
$dumpall
b101 0
b100 /
b1 .
b0 -
b10 ,
b11 +
$end
#0
$dumpvars
bx <
bx ;
bx :
b0 9
08
07
bx 6
05
b100111000100000 4
03
02
01
1*
0)
0(
0'
b1000110010100 &
0%
bx $
0#
bx "
b100111000100000 !
$end
#10
b0 <
b0 ;
b0 :
b0 6
b0 9
1)
0*
#20
b1 9
0)
1'
1*
#30
b0xxxx ;
b1 6
1)
#40
0)
b1 "
0'
#50
b0xxxx0001 ;
1)
#60
0)
#70
b0xxxx00010001 ;
1)
#80
0)
b1001 "
#90
bx000100011001 ;
1)
#100
0)
b100 "
#110
b1000110010100 ;
1)
#120
b101 9
0)
1#
#130
b11 9
b1100101000100 ;
b101 6
1)
#140
b11 9
0)
b11101010011000 $
0#
#150
b1001010001000100 ;
b11 6
1)
#160
b0 9
12
b1000100010111000 4
0)
1%
#170
b100111000100000 4
02
b100010001000100 ;
b0 6
1)
#180
0)
b0 $
0%
#190
1)
#200
b1 9
0)
b1 "
1'
#210
b100010001000001 ;
b1 6
1)
#220
0)
#230
b100010000010001 ;
1)
#240
0)
0'
b1001 "
#250
b100000100011001 ;
1)
#260
0)
b100 "
#270
b1000110010100 ;
1)
#280
b101 9
0)
1(
1#
#290
b100 9
b1100101000100 ;
b101 6
1)
#300
b100 9
0)
b11101010011000 $
0#
#310
b1001010001000100 ;
b100 6
1)
#320
b0 9
15
12
b1001110001000 4
0)
0(
1%
#330
b100111000100000 4
02
05
b100010001000100 ;
b0 6
1)
#340
0)
b0 $
0%
#350
1)
#360
b1 9
0)
b1 "
1'
#370
b100010001000001 ;
b1 6
1)
#380
0)
#390
b100010000010001 ;
1)
#400
0)
0'
b1001 "
#410
b100000100011001 ;
1)
#420
0)
b101 "
#430
b1000110010101 ;
1)
#440
b1 <
18
0)
1#
#450
b10 <
18
b1100101010101 ;
b1 :
1)
#460
b1 <
08
0)
0#
#470
b1001010101010101 ;
1)
#480
b10 <
18
0)
1#
#490
b11 <
11
08
b101010101010101 ;
b10 :
1)
#500
b10 <
01
0)
0#
#510
1)
#520
b11 <
11
0)
1#
#530
b10 9
13
01
b11 :
1)
#540
b10 9
13
0)
0#
#550
13
b10 6
1)
