tarea5/generadorSPI.v
module spi_generator (  
    input wire CLK,           // Reloj del sistema  
    input wire RESET,         // Señal de reinicio  
    input wire CKP,           // Polaridad del reloj  
    input wire CPH,           // Fase del reloj  
    input wire [7:0] data_in, // Datos a enviar  
    output reg CS,            // Chip Select  
    output wire SCK,          // Reloj SPI  
    output reg MOSI,          // Master Out Slave In  
    input wire MISO,          // Master In Slave Out  
    output reg [7:0] data_out // Datos recibidos  
);  

reg [7:0] data_shift_reg;      // Registro para desplazar datos de entrada
reg [1:0] contador_sck, prox_contador_sck;
reg SCK_prev;
reg [2:0] EstPresente, ProxEstado;
reg [3:0] bit_counter, prox_bit_counter;

localparam IDLE = 3'b000;
localparam DATA = 3'b001;

// Generación del reloj SPI a 1/4 de la frecuencia de CLK
always @(posedge CLK) begin
    if (!RESET) begin
        SCK_prev     <= 1'b0;
        contador_sck <= 2'b00;
        CS           <= 1'b1;
        EstPresente  <= IDLE;
        data_shift_reg <= data_in;  // Cargar el valor de data_in al registro de desplazamiento
        data_out <= 8'b0;           // Resetear data_out al inicio
        bit_counter <= 0;
    end else begin
        contador_sck <= prox_contador_sck;
        SCK_prev     <= SCK;
        EstPresente  <= ProxEstado;
        bit_counter  <= prox_bit_counter;

        if (flanco_dezplazamiento && EstPresente == DATA)begin
            data_shift_reg[0] <= MISO;
            data_shift_reg[1] <= data_shift_reg[0];
            data_shift_reg[2] <= data_shift_reg[1];
            data_shift_reg[3] <= data_shift_reg[2];
            data_shift_reg[4] <= data_shift_reg[3];
            data_shift_reg[5] <= data_shift_reg[4];
            data_shift_reg[6] <= data_shift_reg[5];
            data_shift_reg[7] <= data_shift_reg[6];
        end


    end
end

always @(*) begin
    prox_contador_sck = contador_sck + 1;
end

assign SCK = (EstPresente == IDLE && CKP) ? 1 : (EstPresente == IDLE && !CKP) ? 0 : contador_sck[1];
assign posedge_sck = SCK && !SCK_prev && RESET; // Identifica el flanco positivo
assign negedge_sck = !SCK && SCK_prev && RESET; // Identifica el flanco negativo

// Asignación de flanco basado en CPH
assign flanco_muestreo = ((CPH == 1'b0 && CKP == 1'b0) || (CPH == 1'b0 && CKP == 1'b1)) ? posedge_sck : negedge_sck;
assign flanco_dezplazamiento = ((CPH == 1'b0 && CKP == 1'b0) || (CPH == 1'b0 && CKP == 1'b1)) ? negedge_sck : posedge_sck;

always @(*) begin
    ProxEstado = EstPresente;
    prox_bit_counter = bit_counter;

    case (EstPresente)
        IDLE: begin
            CS = 1'b1;
            ProxEstado = DATA;
            prox_bit_counter = 4'd8;
            data_shift_reg <= data_in;  // Cargar el valor de data_in al registro de desplazamiento
        end
        DATA: begin
    CS = 1'b0;
    
    if (flanco_muestreo) begin
        MOSI = data_shift_reg[7];
        ProxEstado = DATA;
        
    end else if (flanco_dezplazamiento) begin
        prox_bit_counter = bit_counter - 1;
        if (bit_counter == 0) begin
            ProxEstado = IDLE;
        end else begin
            ProxEstado = DATA;
        end
    end else begin
        ProxEstado = DATA;
    end
end

    endcase
end

endmodule

tarea5/tb.v
`include "generadorSPI.v"

module tb_spi_generator;

  reg CLK;
  reg RESET;
  reg CKP;
  reg CPH;
  reg [7:0] data_in;
  wire CS;
  wire SCK;
  wire MOSI;
  reg MISO;
  wire [7:0] data_out;

  spi_generator uut (
    .CLK(CLK),
    .RESET(RESET),
    .CKP(CKP),
    .CPH(CPH),
    .data_in(data_in),
    .CS(CS),
    .SCK(SCK),
    .MOSI(MOSI),
    .MISO(MISO),
    .data_out(data_out)
  );

  initial begin
    // Initialize inputs
    CLK = 0;
    RESET = 0;
    CKP = 0;
    CPH = 0;
    data_in = 8'd1;
    MISO = 0;

    // Apply reset
    #10 RESET = 1;


    // Complete simulation after sufficient time
    #400 $finish;
  end

  always #5 CLK = ~CLK; // Clock generation with a period of 10 time units

  initial begin
    // Enable wave dumping
    $dumpfile("resultados.vcd");
    $dumpvars(0, tb_spi_generator);
  end

endmodule

tarea5/resultados.vcd
$date
	Thu Nov 07 16:17:27 2024
$end
$version
	Icarus Verilog
$end
$timescale
	1s
$end
$scope module tb_spi_generator $end
$var wire 8 ! data_out [7:0] $end
$var wire 1 " SCK $end
$var wire 1 # MOSI $end
$var wire 1 $ CS $end
$var reg 1 % CKP $end
$var reg 1 & CLK $end
$var reg 1 ' CPH $end
$var reg 1 ( MISO $end
$var reg 1 ) RESET $end
$var reg 8 * data_in [7:0] $end
$scope module uut $end
$var wire 1 % CKP $end
$var wire 1 & CLK $end
$var wire 1 ' CPH $end
$var wire 1 ( MISO $end
$var wire 1 ) RESET $end
$var wire 8 + data_in [7:0] $end
$var wire 1 , negedge_sck $end
$var wire 1 - posedge_sck $end
$var wire 1 . flanco_muestreo $end
$var wire 1 / flanco_dezplazamiento $end
$var wire 1 " SCK $end
$var parameter 3 0 DATA $end
$var parameter 3 1 IDLE $end
$var reg 1 $ CS $end
$var reg 3 2 EstPresente [2:0] $end
$var reg 1 # MOSI $end
$var reg 3 3 ProxEstado [2:0] $end
$var reg 1 4 SCK_prev $end
$var reg 4 5 bit_counter [3:0] $end
$var reg 2 6 contador_sck [1:0] $end
$var reg 8 7 data_out [7:0] $end
$var reg 8 8 data_shift_reg [7:0] $end
$var reg 4 9 prox_bit_counter [3:0] $end
$var reg 2 : prox_contador_sck [1:0] $end
$upscope $end
$upscope $end
$enddefinitions $end
$comment Show the parameter values. $end
$dumpall
b0 1
b1 0
$end
#0
$dumpvars
bx :
bx 9
bx 8
bx 7
bx 6
bx 5
x4
bx 3
bx 2
0/
0.
0-
0,
b1 +
b1 *
0)
0(
0'
0&
0%
x$
x#
x"
bx !
$end
#5
0"
b1000 9
b1 3
b1 :
b0 5
b0 !
b0 7
b1 8
b0 2
1$
b0 6
04
1&
#10
0&
1)
#15
0$
b10 :
b1000 5
b1 2
b1 6
1&
#20
0&
#25
0#
1.
1-
1"
b11 :
b10 6
1&
#30
0&
#35
0.
0-
b0 :
14
b11 6
1&
#40
0&
#45
b111 9
1/
1,
0"
b1 :
b0 6
1&
#50
0&
#55
0/
0,
b111 9
b10 :
b10 8
b111 5
04
b1 6
1&
#60
0&
#65
1.
1-
1"
b11 :
b10 6
1&
#70
0&
#75
0.
0-
b0 :
14
b11 6
1&
#80
0&
#85
b110 9
1/
1,
0"
b1 :
b0 6
1&
#90
0&
#95
0/
0,
b110 9
b10 :
b100 8
b110 5
04
b1 6
1&
#100
0&
#105
1.
1-
1"
b11 :
b10 6
1&
#110
0&
#115
0.
0-
b0 :
14
b11 6
1&
#120
0&
#125
b101 9
1/
1,
0"
b1 :
b0 6
1&
#130
0&
#135
0/
0,
b101 9
b10 :
b1000 8
b101 5
04
b1 6
1&
#140
0&
#145
1.
1-
1"
b11 :
b10 6
1&
#150
0&
#155
0.
0-
b0 :
14
b11 6
1&
#160
0&
#165
b100 9
1/
1,
0"
b1 :
b0 6
1&
#170
0&
#175
0/
0,
b100 9
b10 :
b10000 8
b100 5
04
b1 6
1&
#180
0&
#185
1.
1-
1"
b11 :
b10 6
1&
#190
0&
#195
0.
0-
b0 :
14
b11 6
1&
#200
0&
#205
b11 9
1/
1,
0"
b1 :
b0 6
1&
#210
0&
#215
0/
0,
b11 9
b10 :
b100000 8
b11 5
04
b1 6
1&
#220
0&
#225
1.
1-
1"
b11 :
b10 6
1&
#230
0&
#235
0.
0-
b0 :
14
b11 6
1&
#240
0&
#245
b10 9
1/
1,
0"
b1 :
b0 6
1&
#250
0&
#255
0/
0,
b10 9
b10 :
b1000000 8
b10 5
04
b1 6
1&
#260
0&
#265
1.
1-
1"
b11 :
b10 6
1&
#270
0&
#275
0.
0-
b0 :
14
b11 6
1&
#280
0&
#285
b1 9
1/
1,
0"
b1 :
b0 6
1&
#290
0&
#295
0/
0,
b1 9
b10 :
b10000000 8
b1 5
04
b1 6
1&
#300
0&
#305
1#
1.
1-
1"
b11 :
b10 6
1&
#310
0&
#315
0.
0-
b0 :
14
b11 6
1&
#320
0&
#325
b0 9
1/
1,
0"
b1 :
b0 6
1&
#330
0&
#335
0/
0,
b1 3
b0 9
b10 :
b0 8
b0 5
04
b1 6
1&
#340
0&
#345
0#
1.
1-
1"
b11 :
b10 6
1&
#350
0&
#355
0.
0-
b0 :
14
b11 6
1&
#360
0&
#365
b0 3
b1111 9
1/
1,
0"
b1 :
b0 6
1&
#370
0&
#375
b1 8
0/
0,
b1000 9
b1 3
1$
b10 :
b1111 5
b0 2
04
b1 6
1&
#380
0&
#385
1.
1-
1"
0$
b11 :
b1000 5
b1 2
b10 6
1&
#390
0&
#395
0.
0-
b0 :
14
b11 6
1&
#400
0&
#405
b111 9
1/
1,
0"
b1 :
b0 6
1&
